[
  {
    "枠名": "【#初配信】初めまして、妃玖です。【妃玖 / RK Music】#妃玖初配信",
    "song_id": "S0456",
    "補足情報": "",
    "歌唱順": "1",
    "配信日": "2026-02-22",
    "枠URL": "https://www.youtube.com/live/FBeA6Zd4aIY?si=5Hba8ojUjGRneshN&t=100",
    "曲終了時間": "",
    "コラボ相手様": "なし",
    "キー": ""
  },
  {
    "枠名": "【#初配信】初めまして、妃玖です。【妃玖 / RK Music】#妃玖初配信",
    "song_id": "S0457",
    "補足情報": "",
    "歌唱順": "2",
    "配信日": "2026-02-22",
    "枠URL": "https://www.youtube.com/live/FBeA6Zd4aIY?si=Owat2FZmFWmZQ0Wh&t=310",
    "曲終了時間": "",
    "コラボ相手様": "なし",
    "キー": ""
  },
  {
    "枠名": "【#初配信】初めまして、妃玖です。【妃玖 / RK Music】#妃玖初配信",
    "song_id": "S0458",
    "補足情報": "",
    "歌唱順": "3",
    "配信日": "2026-02-22",
    "枠URL": "https://www.youtube.com/live/FBeA6Zd4aIY?si=Owat2FZmFWmZQ0Wh&t=455",
    "曲終了時間": "",
    "コラボ相手様": "なし",
    "キー": ""
  },
  {
    "枠名": "【#初配信】初めまして、妃玖です。【妃玖 / RK Music】#妃玖初配信",
    "song_id": "S0153",
    "補足情報": "",
    "歌唱順": "4",
    "配信日": "2026-02-22",
    "枠URL": "https://www.youtube.com/live/FBeA6Zd4aIY?si=O6__UrGeZNel4e00&t=667",
    "曲終了時間": "",
    "コラボ相手様": "なし",
    "キー": ""
  },
  {
    "枠名": "【#初配信】初めまして、妃玖です。【妃玖 / RK Music】#妃玖初配信",
    "song_id": "S0393",
    "補足情報": "",
    "歌唱順": "5",
    "配信日": "2026-02-22",
    "枠URL": "https://www.youtube.com/live/FBeA6Zd4aIY?si=O6__UrGeZNel4e00&t=903",
    "曲終了時間": "",
    "コラボ相手様": "なし",
    "キー": ""
  },
  {
    "枠名": "【#初配信】初めまして、妃玖です。【妃玖 / RK Music】#妃玖初配信",
    "song_id": "S0458",
    "補足情報": "",
    "歌唱順": "6",
    "配信日": "2026-02-22",
    "枠URL": "https://www.youtube.com/live/FBeA6Zd4aIY?si=O6__UrGeZNel4e00&t=1435",
    "曲終了時間": "",
    "コラボ相手様": "なし",
    "キー": ""
  },
  {
    "枠名": "【自己紹介/雑談/歌】色々話そう。",
    "song_id": "S0065",
    "補足情報": "",
    "歌唱順": "1",
    "配信日": "2026-02-23",
    "枠URL": "https://www.youtube.com/live/fDVXhtnfDSc?si=iZ0oOfIuq-32zc2o&t=6227",
    "曲終了時間": "",
    "コラボ相手様": "なし",
    "キー": ""
  },
  {
    "枠名": "【自己紹介/雑談/歌】色々話そう。",
    "song_id": "S0177",
    "補足情報": "",
    "歌唱順": "2",
    "配信日": "2026-02-23",
    "枠URL": "https://www.youtube.com/live/fDVXhtnfDSc?si=iZ0oOfIuq-32zc2o&t=7162",
    "曲終了時間": "",
    "コラボ相手様": "なし",
    "キー": ""
  },
  {
    "枠名": "【自己紹介/雑談/歌】色々話そう。",
    "song_id": "S0123",
    "補足情報": "",
    "歌唱順": "3",
    "配信日": "2026-02-23",
    "枠URL": "https://www.youtube.com/live/fDVXhtnfDSc?si=iZ0oOfIuq-32zc2o&t=8409",
    "曲終了時間": "",
    "コラボ相手様": "なし",
    "キー": ""
  },
  {
    "枠名": "【歌/雑談】急に寒いね、外が。",
    "song_id": "S0115",
    "補足情報": "",
    "歌唱順": "1",
    "配信日": "2026-02-25",
    "枠URL": "https://www.youtube.com/live/V_wtPmGOF7I?si=Yl-alpJSEMwHm7mO&t=665",
    "曲終了時間": "",
    "コラボ相手様": "なし",
    "キー": ""
  },
  {
    "枠名": "【歌/雑談】急に寒いね、外が。",
    "song_id": "S0034",
    "補足情報": "",
    "歌唱順": "2",
    "配信日": "2026-02-25",
    "枠URL": "https://www.youtube.com/live/V_wtPmGOF7I?si=Yl-alpJSEMwHm7mO&t=2479",
    "曲終了時間": "",
    "コラボ相手様": "なし",
    "キー": ""
  },
  {
    "枠名": "【歌/雑談】急に寒いね、外が。",
    "song_id": "S0459",
    "補足情報": "",
    "歌唱順": "3",
    "配信日": "2026-02-25",
    "枠URL": "https://www.youtube.com/live/V_wtPmGOF7I?si=Yl-alpJSEMwHm7mO&t=4693",
    "曲終了時間": "",
    "コラボ相手様": "なし",
    "キー": ""
  },
  {
    "枠名": "【歌/雑談】急に寒いね、外が。",
    "song_id": "S0262",
    "補足情報": "",
    "歌唱順": "4",
    "配信日": "2026-02-25",
    "枠URL": "https://www.youtube.com/live/V_wtPmGOF7I?si=Yl-alpJSEMwHm7mO&t=6242",
    "曲終了時間": "",
    "コラボ相手様": "なし",
    "キー": ""
  },
  {
    "枠名": "【歌/雑談】急に寒いね、外が。",
    "song_id": "S0460",
    "補足情報": "",
    "歌唱順": "5",
    "配信日": "2026-02-25",
    "枠URL": "https://www.youtube.com/live/V_wtPmGOF7I?si=Yl-alpJSEMwHm7mO&t=7785",
    "曲終了時間": "",
    "コラボ相手様": "なし",
    "キー": ""
  },
  {
    "枠名": "【歌/雑談】急に寒いね、外が。",
    "song_id": "S0116",
    "補足情報": "",
    "歌唱順": "6",
    "配信日": "2026-02-25",
    "枠URL": "https://www.youtube.com/live/V_wtPmGOF7I?si=Yl-alpJSEMwHm7mO&t=9194",
    "曲終了時間": "",
    "コラボ相手様": "なし",
    "キー": ""
  },
  {
    "枠名": "【歌/雑談】急に寒いね、外が。",
    "song_id": "S0043",
    "補足情報": "",
    "歌唱順": "7",
    "配信日": "2026-02-25",
    "枠URL": "https://www.youtube.com/live/V_wtPmGOF7I?si=Yl-alpJSEMwHm7mO&t=9674",
    "曲終了時間": "",
    "コラボ相手様": "なし",
    "キー": ""
  },
  {
    "枠名": "【歌/雑談】急に寒いね、外が。",
    "song_id": "S0191",
    "補足情報": "",
    "歌唱順": "8",
    "配信日": "2026-02-25",
    "枠URL": "https://www.youtube.com/live/V_wtPmGOF7I?si=Yl-alpJSEMwHm7mO&t=10129",
    "曲終了時間": "",
    "コラボ相手様": "なし",
    "キー": ""
  },
  {
    "枠名": "【歌/雑談】急に寒いね、外が。",
    "song_id": "S0139",
    "補足情報": "",
    "歌唱順": "9",
    "配信日": "2026-02-25",
    "枠URL": "https://www.youtube.com/live/V_wtPmGOF7I?si=Yl-alpJSEMwHm7mO&t=10667",
    "曲終了時間": "",
    "コラボ相手様": "なし",
    "キー": ""
  },
  {
    "枠名": "【歌/雑談】今日もおつかれ！",
    "song_id": "S0461",
    "補足情報": "",
    "歌唱順": "1",
    "配信日": "2026-02-27",
    "枠URL": "https://www.youtube.com/live/yGJRsAs3Ee0?si=RgLjhprIsIzAY1WE&t=490",
    "曲終了時間": "",
    "コラボ相手様": "なし",
    "キー": ""
  },
  {
    "枠名": "【歌/雑談】今日もおつかれ！",
    "song_id": "S0387",
    "補足情報": "",
    "歌唱順": "2",
    "配信日": "2026-02-27",
    "枠URL": "https://www.youtube.com/live/yGJRsAs3Ee0?si=RgLjhprIsIzAY1WE&t=1160",
    "曲終了時間": "",
    "コラボ相手様": "なし",
    "キー": ""
  },
  {
    "枠名": "【歌/雑談】今日もおつかれ！",
    "song_id": "S0462",
    "補足情報": "",
    "歌唱順": "3",
    "配信日": "2026-02-27",
    "枠URL": "https://www.youtube.com/live/yGJRsAs3Ee0?si=RgLjhprIsIzAY1WE&t=2088",
    "曲終了時間": "",
    "コラボ相手様": "なし",
    "キー": ""
  },
  {
    "枠名": "【歌/雑談】今日もおつかれ！",
    "song_id": "S0051",
    "補足情報": "",
    "歌唱順": "4",
    "配信日": "2026-02-27",
    "枠URL": "https://www.youtube.com/live/yGJRsAs3Ee0?si=RgLjhprIsIzAY1WE&t=2951",
    "曲終了時間": "",
    "コラボ相手様": "なし",
    "キー": ""
  },
  {
    "枠名": "【歌/雑談】今日もおつかれ！",
    "song_id": "S0463",
    "補足情報": "",
    "歌唱順": "5",
    "配信日": "2026-02-27",
    "枠URL": "https://www.youtube.com/live/yGJRsAs3Ee0?si=RgLjhprIsIzAY1WE&t=3458",
    "曲終了時間": "",
    "コラボ相手様": "なし",
    "キー": ""
  },
  {
    "枠名": "【歌/雑談】今日もおつかれ！",
    "song_id": "S0464",
    "補足情報": "",
    "歌唱順": "6",
    "配信日": "2026-02-27",
    "枠URL": "https://www.youtube.com/live/yGJRsAs3Ee0?si=RgLjhprIsIzAY1WE&t=4205",
    "曲終了時間": "",
    "コラボ相手様": "なし",
    "キー": ""
  },
  {
    "枠名": "【歌/雑談】今日もおつかれ！",
    "song_id": "S0095",
    "補足情報": "",
    "歌唱順": "7",
    "配信日": "2026-02-27",
    "枠URL": "https://www.youtube.com/live/yGJRsAs3Ee0?si=RgLjhprIsIzAY1WE&t=4638",
    "曲終了時間": "",
    "コラボ相手様": "なし",
    "キー": ""
  },
  {
    "枠名": "【歌/雑談】今日もおつかれ！",
    "song_id": "S0076",
    "補足情報": "",
    "歌唱順": "8",
    "配信日": "2026-02-27",
    "枠URL": "https://www.youtube.com/live/yGJRsAs3Ee0?si=RgLjhprIsIzAY1WE&t=6690",
    "曲終了時間": "",
    "コラボ相手様": "なし",
    "キー": ""
  },
  {
    "枠名": "【歌/雑談】今日もおつかれ！",
    "song_id": "S0207",
    "補足情報": "",
    "歌唱順": "9",
    "配信日": "2026-02-27",
    "枠URL": "https://www.youtube.com/live/yGJRsAs3Ee0?si=RgLjhprIsIzAY1WE&t=8207",
    "曲終了時間": "",
    "コラボ相手様": "なし",
    "キー": ""
  },
  {
    "枠名": "【歌/雑談】やぁ。",
    "song_id": "S0465",
    "補足情報": "",
    "歌唱順": "1",
    "配信日": "2026-03-04",
    "枠URL": "https://www.youtube.com/live/6LWMbxPC0l0?si=xq7VZwWDsu3qtLhl&t=3023",
    "曲終了時間": "",
    "コラボ相手様": "なし",
    "キー": ""
  },
  {
    "枠名": "【歌/雑談】やぁ。",
    "song_id": "S0466",
    "補足情報": "",
    "歌唱順": "2",
    "配信日": "2026-03-04",
    "枠URL": "https://www.youtube.com/live/6LWMbxPC0l0?si=xq7VZwWDsu3qtLhl&t=3509",
    "曲終了時間": "",
    "コラボ相手様": "なし",
    "キー": ""
  },
  {
    "枠名": "【歌/雑談】やぁ。",
    "song_id": "S0249",
    "補足情報": "",
    "歌唱順": "3",
    "配信日": "2026-03-04",
    "枠URL": "https://www.youtube.com/live/6LWMbxPC0l0?si=xq7VZwWDsu3qtLhl&t=5656",
    "曲終了時間": "",
    "コラボ相手様": "なし",
    "キー": ""
  },
  {
    "枠名": "【歌/雑談】やぁ。",
    "song_id": "S0467",
    "補足情報": "",
    "歌唱順": "4",
    "配信日": "2026-03-04",
    "枠URL": "https://www.youtube.com/live/6LWMbxPC0l0?si=xq7VZwWDsu3qtLhl&t=8186",
    "曲終了時間": "",
    "コラボ相手様": "なし",
    "キー": ""
  },
  {
    "枠名": "【歌/雑談】やぁ。",
    "song_id": "S0468",
    "補足情報": "",
    "歌唱順": "5",
    "配信日": "2026-03-04",
    "枠URL": "https://www.youtube.com/live/6LWMbxPC0l0?si=xq7VZwWDsu3qtLhl&t=10885",
    "曲終了時間": "",
    "コラボ相手様": "なし",
    "キー": ""
  },
  {
    "枠名": "【雑談】歌も少し！いよいよ明日！",
    "song_id": "S0010",
    "補足情報": "",
    "歌唱順": "1",
    "配信日": "2026-03-07",
    "枠URL": "https://www.youtube.com/live/-0pd-iRooQg?si=ZmJmFMJspk0VWsWr&t=122",
    "曲終了時間": "",
    "コラボ相手様": "なし",
    "キー": ""
  },
  {
    "枠名": "【雑談】歌も少し！いよいよ明日！",
    "song_id": "S0469",
    "補足情報": "",
    "歌唱順": "2",
    "配信日": "2026-03-07",
    "枠URL": "https://www.youtube.com/live/-0pd-iRooQg?si=ZmJmFMJspk0VWsWr&t=2274",
    "曲終了時間": "",
    "コラボ相手様": "なし",
    "キー": ""
  },
  {
    "枠名": "【雑談】歌も少し！いよいよ明日！",
    "song_id": "S0323",
    "補足情報": "",
    "歌唱順": "3",
    "配信日": "2026-03-07",
    "枠URL": "https://www.youtube.com/live/-0pd-iRooQg?si=ZmJmFMJspk0VWsWr&t=3473",
    "曲終了時間": "",
    "コラボ相手様": "なし",
    "キー": ""
  },
  {
    "枠名": "【雑談】歌も少し！いよいよ明日！",
    "song_id": "S0458",
    "補足情報": "",
    "歌唱順": "4",
    "配信日": "2026-03-07",
    "枠URL": "https://www.youtube.com/live/-0pd-iRooQg?si=ZmJmFMJspk0VWsWr&t=4020",
    "曲終了時間": "",
    "コラボ相手様": "なし",
    "キー": ""
  },
  {
    "枠名": "【祝！収益化記念配信】ありがとうすぎ！ライブ振り返りも！#妃玖ノ記録【妃玖/RKmusic/Fused】",
    "song_id": "S0470",
    "補足情報": "",
    "歌唱順": "1",
    "配信日": "2026-03-11",
    "枠URL": "https://www.youtube.com/live/UYZvCpQVWvY?si=jabGvYmi6YuUWVkR&t=120",
    "曲終了時間": "",
    "コラボ相手様": "なし",
    "キー": ""
  },
  {
    "枠名": "【祝！収益化記念配信】ありがとうすぎ！ライブ振り返りも！#妃玖ノ記録【妃玖/RKmusic/Fused】",
    "song_id": "S0107",
    "補足情報": "",
    "歌唱順": "2",
    "配信日": "2026-03-11",
    "枠URL": "https://www.youtube.com/live/UYZvCpQVWvY?si=jabGvYmi6YuUWVkR&t=873",
    "曲終了時間": "",
    "コラボ相手様": "なし",
    "キー": ""
  },
  {
    "枠名": "【祝！収益化記念配信】ありがとうすぎ！ライブ振り返りも！#妃玖ノ記録【妃玖/RKmusic/Fused】",
    "song_id": "S0250",
    "補足情報": "",
    "歌唱順": "3",
    "配信日": "2026-03-11",
    "枠URL": "https://www.youtube.com/live/UYZvCpQVWvY?si=jabGvYmi6YuUWVkR&t=3100",
    "曲終了時間": "",
    "コラボ相手様": "なし",
    "キー": ""
  },
  {
    "枠名": "【祝！収益化記念配信】ありがとうすぎ！ライブ振り返りも！#妃玖ノ記録【妃玖/RKmusic/Fused】",
    "song_id": "S0471",
    "補足情報": "",
    "歌唱順": "4",
    "配信日": "2026-03-11",
    "枠URL": "https://www.youtube.com/live/UYZvCpQVWvY?si=jabGvYmi6YuUWVkR&t=3318",
    "曲終了時間": "",
    "コラボ相手様": "なし",
    "キー": ""
  },
  {
    "枠名": "【祝！収益化記念配信】ありがとうすぎ！ライブ振り返りも！#妃玖ノ記録【妃玖/RKmusic/Fused】",
    "song_id": "S0253",
    "補足情報": "",
    "歌唱順": "5",
    "配信日": "2026-03-11",
    "枠URL": "https://www.youtube.com/live/UYZvCpQVWvY?si=jabGvYmi6YuUWVkR&t=4685",
    "曲終了時間": "",
    "コラボ相手様": "なし",
    "キー": ""
  },
  {
    "枠名": "【祝！収益化記念配信】ありがとうすぎ！ライブ振り返りも！#妃玖ノ記録【妃玖/RKmusic/Fused】",
    "song_id": "S0109",
    "補足情報": "",
    "歌唱順": "6",
    "配信日": "2026-03-11",
    "枠URL": "https://www.youtube.com/live/UYZvCpQVWvY?si=jabGvYmi6YuUWVkR&t=4895",
    "曲終了時間": "",
    "コラボ相手様": "なし",
    "キー": ""
  },
  {
    "枠名": "【祝！収益化記念配信】ありがとうすぎ！ライブ振り返りも！#妃玖ノ記録【妃玖/RKmusic/Fused】",
    "song_id": "S0473",
    "補足情報": "",
    "歌唱順": "7",
    "配信日": "2026-03-11",
    "枠URL": "https://www.youtube.com/live/UYZvCpQVWvY?si=jabGvYmi6YuUWVkR&t=5881",
    "曲終了時間": "",
    "コラボ相手様": "なし",
    "キー": ""
  },
  {
    "枠名": "【祝！収益化記念配信】ありがとうすぎ！ライブ振り返りも！#妃玖ノ記録【妃玖/RKmusic/Fused】",
    "song_id": "S0474",
    "補足情報": "",
    "歌唱順": "8",
    "配信日": "2026-03-11",
    "枠URL": "https://www.youtube.com/live/UYZvCpQVWvY?si=jabGvYmi6YuUWVkR&t=6460",
    "曲終了時間": "",
    "コラボ相手様": "なし",
    "キー": ""
  },
  {
    "枠名": "【祝！収益化記念配信】ありがとうすぎ！ライブ振り返りも！#妃玖ノ記録【妃玖/RKmusic/Fused】",
    "song_id": "S0455",
    "補足情報": "",
    "歌唱順": "9",
    "配信日": "2026-03-11",
    "枠URL": "https://www.youtube.com/live/UYZvCpQVWvY?si=jabGvYmi6YuUWVkR&t=8383",
    "曲終了時間": "",
    "コラボ相手様": "なし",
    "キー": ""
  },
  {
    "枠名": "【祝！収益化記念配信】ありがとうすぎ！ライブ振り返りも！#妃玖ノ記録【妃玖/RKmusic/Fused】",
    "song_id": "S0475",
    "補足情報": "",
    "歌唱順": "10",
    "配信日": "2026-03-11",
    "枠URL": "https://www.youtube.com/live/UYZvCpQVWvY?si=jabGvYmi6YuUWVkR&t=9633",
    "曲終了時間": "",
    "コラボ相手様": "なし",
    "キー": ""
  },
  {
    "枠名": "【ｹﾞﾘﾗ歌枠】歌を、歌うし。おしゃべりも、する。【妃玖/RKmusic/Fused】",
    "song_id": "S0023",
    "補足情報": "",
    "歌唱順": "1",
    "配信日": "2026-03-16",
    "枠URL": "https://www.youtube.com/live/qlYqFWBex84?si=rkJd2ec0E72XXYrB&t=954",
    "曲終了時間": "",
    "コラボ相手様": "なし",
    "キー": ""
  },
  {
    "枠名": "【ｹﾞﾘﾗ歌枠】歌を、歌うし。おしゃべりも、する。【妃玖/RKmusic/Fused】",
    "song_id": "S0160",
    "補足情報": "",
    "歌唱順": "2",
    "配信日": "2026-03-16",
    "枠URL": "https://www.youtube.com/live/qlYqFWBex84?si=c9z_ATrd2a78HEe6&t=5118",
    "曲終了時間": "",
    "コラボ相手様": "なし",
    "キー": ""
  },
  {
    "枠名": "【ｹﾞﾘﾗ歌枠】歌を、歌うし。おしゃべりも、する。【妃玖/RKmusic/Fused】",
    "song_id": "S0219",
    "補足情報": "",
    "歌唱順": "3",
    "配信日": "2026-03-16",
    "枠URL": "https://www.youtube.com/live/qlYqFWBex84?si=vzwcIV9WTP4RwwOe&t=6037",
    "曲終了時間": "",
    "コラボ相手様": "なし",
    "キー": ""
  },
  {
    "枠名": "【ｹﾞﾘﾗ歌枠】歌を、歌うし。おしゃべりも、する。【妃玖/RKmusic/Fused】",
    "song_id": "S0451",
    "補足情報": "",
    "歌唱順": "4",
    "配信日": "2026-03-16",
    "枠URL": "https://www.youtube.com/live/qlYqFWBex84?si=otdGSf9AKJUwGTzE&t=6600",
    "曲終了時間": "",
    "コラボ相手様": "なし",
    "キー": ""
  },
  {
    "枠名": "【ｹﾞﾘﾗ歌枠】歌を、歌うし。おしゃべりも、する。【妃玖/RKmusic/Fused】",
    "song_id": "S0476",
    "補足情報": "",
    "歌唱順": "5",
    "配信日": "2026-03-16",
    "枠URL": "https://www.youtube.com/live/qlYqFWBex84?si=hgmLaIL91OJmiJDh&t=7055",
    "曲終了時間": "",
    "コラボ相手様": "なし",
    "キー": ""
  },
  {
    "枠名": "【祝！メンシ解禁記念】メンシ解禁じゃー！🐍 #妃玖ノ記録【妃玖/RKmusic/Fused】",
    "song_id": "S0272",
    "補足情報": "",
    "歌唱順": "1",
    "配信日": "2026-03-19",
    "枠URL": "https://www.youtube.com/live/qaKaid9bZ18?t=1680",
    "曲終了時間": "",
    "コラボ相手様": "なし",
    "キー": ""
  },
  {
    "枠名": "【祝！メンシ解禁記念】メンシ解禁じゃー！🐍 #妃玖ノ記録【妃玖/RKmusic/Fused】",
    "song_id": "S0477",
    "補足情報": "",
    "歌唱順": "2",
    "配信日": "2026-03-19",
    "枠URL": "https://www.youtube.com/live/qaKaid9bZ18?t=2970",
    "曲終了時間": "",
    "コラボ相手様": "なし",
    "キー": ""
  },
  {
    "枠名": "【祝！メンシ解禁記念】メンシ解禁じゃー！🐍 #妃玖ノ記録【妃玖/RKmusic/Fused】",
    "song_id": "S0478",
    "補足情報": "",
    "歌唱順": "3",
    "配信日": "2026-03-19",
    "枠URL": "https://www.youtube.com/live/qaKaid9bZ18?t=3763",
    "曲終了時間": "",
    "コラボ相手様": "なし",
    "キー": ""
  },
  {
    "枠名": "【祝！メンシ解禁記念】メンシ解禁じゃー！🐍 #妃玖ノ記録【妃玖/RKmusic/Fused】",
    "song_id": "S0010",
    "補足情報": "",
    "歌唱順": "4",
    "配信日": "2026-03-19",
    "枠URL": "https://www.youtube.com/live/qaKaid9bZ18?t=5123",
    "曲終了時間": "",
    "コラボ相手様": "なし",
    "キー": ""
  },
  {
    "枠名": "【祝！メンシ解禁記念】メンシ解禁じゃー！🐍 #妃玖ノ記録【妃玖/RKmusic/Fused】",
    "song_id": "S0209",
    "補足情報": "",
    "歌唱順": "5",
    "配信日": "2026-03-19",
    "枠URL": "https://www.youtube.com/live/qaKaid9bZ18?t=6233",
    "曲終了時間": "",
    "コラボ相手様": "なし",
    "キー": ""
  },
  {
    "枠名": "【祝！メンシ解禁記念】メンシ解禁じゃー！🐍 #妃玖ノ記録【妃玖/RKmusic/Fused】",
    "song_id": "S0479",
    "補足情報": "",
    "歌唱順": "6",
    "配信日": "2026-03-19",
    "枠URL": "https://www.youtube.com/live/qaKaid9bZ18?t=8414",
    "曲終了時間": "",
    "コラボ相手様": "なし",
    "キー": ""
  },
  {
    "枠名": "【祝！メンシ解禁記念】メンシ解禁じゃー！🐍 #妃玖ノ記録【妃玖/RKmusic/Fused】",
    "song_id": "S0009",
    "補足情報": "",
    "歌唱順": "7",
    "配信日": "2026-03-19",
    "枠URL": "https://www.youtube.com/live/qaKaid9bZ18?t=8808",
    "曲終了時間": "",
    "コラボ相手様": "なし",
    "キー": ""
  },
  {
    "枠名": "【祝！メンシ解禁記念】メンシ解禁じゃー！🐍 #妃玖ノ記録【妃玖/RKmusic/Fused】",
    "song_id": "S0263",
    "補足情報": "",
    "歌唱順": "8",
    "配信日": "2026-03-19",
    "枠URL": "https://www.youtube.com/live/qaKaid9bZ18?t=9109",
    "曲終了時間": "",
    "コラボ相手様": "なし",
    "キー": ""
  },
  {
    "枠名": "【祝！メンシ解禁記念】メンシ解禁じゃー！🐍 #妃玖ノ記録【妃玖/RKmusic/Fused】",
    "song_id": "S0480",
    "補足情報": "",
    "歌唱順": "9",
    "配信日": "2026-03-19",
    "枠URL": "https://www.youtube.com/live/qaKaid9bZ18?t=9356",
    "曲終了時間": "",
    "コラボ相手様": "なし",
    "キー": ""
  },
  {
    "枠名": "【ﾏﾀｰﾘ歌雑】ゆっくりまたーりネ #妃玖ノ記録【妃玖/RKmusic/Fused】",
    "song_id": "S0482",
    "補足情報": "",
    "歌唱順": "1",
    "配信日": "2026-03-25",
    "枠URL": "https://www.youtube.com/live/hW3Zv9iHbes?t=158",
    "曲終了時間": "",
    "コラボ相手様": "なし",
    "キー": ""
  },
  {
    "枠名": "【ﾏﾀｰﾘ歌雑】ゆっくりまたーりネ #妃玖ノ記録【妃玖/RKmusic/Fused】",
    "song_id": "S0483",
    "補足情報": "",
    "歌唱順": "2",
    "配信日": "2026-03-25",
    "枠URL": "https://www.youtube.com/live/hW3Zv9iHbes?t=1437",
    "曲終了時間": "",
    "コラボ相手様": "なし",
    "キー": ""
  },
  {
    "枠名": "【ﾏﾀｰﾘ歌雑】ゆっくりまたーりネ #妃玖ノ記録【妃玖/RKmusic/Fused】",
    "song_id": "S0481",
    "補足情報": "",
    "歌唱順": "3",
    "配信日": "2026-03-25",
    "枠URL": "https://www.youtube.com/live/hW3Zv9iHbes?t=2133",
    "曲終了時間": "",
    "コラボ相手様": "なし",
    "キー": ""
  },
  {
    "枠名": "【ﾏﾀｰﾘ歌雑】ゆっくりまたーりネ #妃玖ノ記録【妃玖/RKmusic/Fused】",
    "song_id": "S0419",
    "補足情報": "",
    "歌唱順": "4",
    "配信日": "2026-03-25",
    "枠URL": "https://www.youtube.com/live/hW3Zv9iHbes?t=4315",
    "曲終了時間": "",
    "コラボ相手様": "なし",
    "キー": ""
  },
  {
    "枠名": "【ﾏﾀｰﾘ歌雑】ゆっくりまたーりネ #妃玖ノ記録【妃玖/RKmusic/Fused】",
    "song_id": "S0399",
    "補足情報": "",
    "歌唱順": "5",
    "配信日": "2026-03-25",
    "枠URL": "https://www.youtube.com/live/hW3Zv9iHbes?t=4611",
    "曲終了時間": "",
    "コラボ相手様": "なし",
    "キー": ""
  },
  {
    "枠名": "【ﾏﾀｰﾘ歌雑】ゆっくりまたーりネ #妃玖ノ記録【妃玖/RKmusic/Fused】",
    "song_id": "S0484",
    "補足情報": "",
    "歌唱順": "6",
    "配信日": "2026-03-25",
    "枠URL": "https://www.youtube.com/live/hW3Zv9iHbes?t=4972",
    "曲終了時間": "",
    "コラボ相手様": "なし",
    "キー": ""
  },
  {
    "枠名": "【ﾏﾀｰﾘ歌雑】ゆっくりまたーりネ #妃玖ノ記録【妃玖/RKmusic/Fused】",
    "song_id": "S0334",
    "補足情報": "",
    "歌唱順": "7",
    "配信日": "2026-03-25",
    "枠URL": "https://www.youtube.com/live/hW3Zv9iHbes?t=6302",
    "曲終了時間": "",
    "コラボ相手様": "なし",
    "キー": ""
  },
  {
    "枠名": "【ﾏﾀｰﾘ歌雑】ゆっくりまたーりネ #妃玖ノ記録【妃玖/RKmusic/Fused】",
    "song_id": "S0485",
    "補足情報": "",
    "歌唱順": "8",
    "配信日": "2026-03-25",
    "枠URL": "https://www.youtube.com/live/hW3Zv9iHbes?t=6600",
    "曲終了時間": "",
    "コラボ相手様": "なし",
    "キー": ""
  },
  {
    "枠名": "【ﾏﾀｰﾘ歌雑】ゆっくりまたーりネ #妃玖ノ記録【妃玖/RKmusic/Fused】",
    "song_id": "S0486",
    "補足情報": "",
    "歌唱順": "9",
    "配信日": "2026-03-25",
    "枠URL": "https://www.youtube.com/live/hW3Zv9iHbes?t=6884",
    "曲終了時間": "",
    "コラボ相手様": "なし",
    "キー": ""
  },
  {
    "枠名": "【ﾏﾀｰﾘ歌雑】ゆっくりまたーりネ #妃玖ノ記録【妃玖/RKmusic/Fused】",
    "song_id": "S0026",
    "補足情報": "",
    "歌唱順": "10",
    "配信日": "2026-03-25",
    "枠URL": "https://www.youtube.com/live/hW3Zv9iHbes?t=8765",
    "曲終了時間": "",
    "コラボ相手様": "なし",
    "キー": ""
  },
  {
    "枠名": "【1ヶ月記念歌枠】あっという間だね、ありがとう #妃玖ノ記録【妃玖/RKmusic/Fused】",
    "song_id": "S0458",
    "補足情報": "",
    "歌唱順": "1",
    "配信日": "2026-03-22",
    "枠URL": "https://www.youtube.com/live/13_IyqNjdFQ?t=168",
    "曲終了時間": "",
    "コラボ相手様": "なし",
    "キー": ""
  },
  {
    "枠名": "【1ヶ月記念歌枠】あっという間だね、ありがとう #妃玖ノ記録【妃玖/RKmusic/Fused】",
    "song_id": "S0475",
    "補足情報": "",
    "歌唱順": "2",
    "配信日": "2026-03-22",
    "枠URL": "https://www.youtube.com/live/13_IyqNjdFQ?t=605",
    "曲終了時間": "",
    "コラボ相手様": "なし",
    "キー": ""
  },
  {
    "枠名": "【1ヶ月記念歌枠】あっという間だね、ありがとう #妃玖ノ記録【妃玖/RKmusic/Fused】",
    "song_id": "S0099",
    "補足情報": "",
    "歌唱順": "3",
    "配信日": "2026-03-22",
    "枠URL": "https://www.youtube.com/live/13_IyqNjdFQ?t=1216",
    "曲終了時間": "",
    "コラボ相手様": "なし",
    "キー": ""
  },
  {
    "枠名": "【1ヶ月記念歌枠】あっという間だね、ありがとう #妃玖ノ記録【妃玖/RKmusic/Fused】",
    "song_id": "S0487",
    "補足情報": "",
    "歌唱順": "4",
    "配信日": "2026-03-22",
    "枠URL": "https://www.youtube.com/live/13_IyqNjdFQ?t=1695",
    "曲終了時間": "",
    "コラボ相手様": "なし",
    "キー": ""
  },
  {
    "枠名": "【1ヶ月記念歌枠】あっという間だね、ありがとう #妃玖ノ記録【妃玖/RKmusic/Fused】",
    "song_id": "S0488",
    "補足情報": "",
    "歌唱順": "5",
    "配信日": "2026-03-22",
    "枠URL": "https://www.youtube.com/live/13_IyqNjdFQ?t=2161",
    "曲終了時間": "",
    "コラボ相手様": "なし",
    "キー": ""
  },
  {
    "枠名": "【1ヶ月記念歌枠】あっという間だね、ありがとう #妃玖ノ記録【妃玖/RKmusic/Fused】",
    "song_id": "S0116",
    "補足情報": "",
    "歌唱順": "6",
    "配信日": "2026-03-22",
    "枠URL": "https://www.youtube.com/live/13_IyqNjdFQ?t=2895",
    "曲終了時間": "",
    "コラボ相手様": "なし",
    "キー": ""
  },
  {
    "枠名": "【1ヶ月記念歌枠】あっという間だね、ありがとう #妃玖ノ記録【妃玖/RKmusic/Fused】",
    "song_id": "S0489",
    "補足情報": "",
    "歌唱順": "7",
    "配信日": "2026-03-22",
    "枠URL": "https://www.youtube.com/live/13_IyqNjdFQ?t=3309",
    "曲終了時間": "",
    "コラボ相手様": "なし",
    "キー": ""
  },
  {
    "枠名": "【1ヶ月記念歌枠】あっという間だね、ありがとう #妃玖ノ記録【妃玖/RKmusic/Fused】",
    "song_id": "S0490",
    "補足情報": "",
    "歌唱順": "8",
    "配信日": "2026-03-22",
    "枠URL": "https://www.youtube.com/live/13_IyqNjdFQ?t=3953",
    "曲終了時間": "",
    "コラボ相手様": "なし",
    "キー": ""
  },
  {
    "枠名": "【1ヶ月記念歌枠】あっという間だね、ありがとう #妃玖ノ記録【妃玖/RKmusic/Fused】",
    "song_id": "S0431",
    "補足情報": "",
    "歌唱順": "9",
    "配信日": "2026-03-22",
    "枠URL": "https://www.youtube.com/live/13_IyqNjdFQ?t=4324",
    "曲終了時間": "",
    "コラボ相手様": "なし",
    "キー": ""
  },
  {
    "枠名": "【1ヶ月記念歌枠】あっという間だね、ありがとう #妃玖ノ記録【妃玖/RKmusic/Fused】",
    "song_id": "S0491",
    "補足情報": "",
    "歌唱順": "10",
    "配信日": "2026-03-22",
    "枠URL": "https://www.youtube.com/live/13_IyqNjdFQ?t=5020",
    "曲終了時間": "",
    "コラボ相手様": "なし",
    "キー": ""
  },
  {
    "枠名": "【1ヶ月記念歌枠】あっという間だね、ありがとう #妃玖ノ記録【妃玖/RKmusic/Fused】",
    "song_id": "S0252",
    "補足情報": "",
    "歌唱順": "11",
    "配信日": "2026-03-22",
    "枠URL": "https://www.youtube.com/live/13_IyqNjdFQ?t=5411",
    "曲終了時間": "",
    "コラボ相手様": "なし",
    "キー": ""
  },
  {
    "枠名": "【1ヶ月記念歌枠】あっという間だね、ありがとう #妃玖ノ記録【妃玖/RKmusic/Fused】",
    "song_id": "S0470",
    "補足情報": "",
    "歌唱順": "12",
    "配信日": "2026-03-22",
    "枠URL": "https://www.youtube.com/live/13_IyqNjdFQ?t=5858",
    "曲終了時間": "",
    "コラボ相手様": "なし",
    "キー": ""
  },
  {
    "枠名": "【1ヶ月記念歌枠】あっという間だね、ありがとう #妃玖ノ記録【妃玖/RKmusic/Fused】",
    "song_id": "S0010",
    "補足情報": "",
    "歌唱順": "13",
    "配信日": "2026-03-22",
    "枠URL": "https://www.youtube.com/live/13_IyqNjdFQ?t=6359",
    "曲終了時間": "",
    "コラボ相手様": "なし",
    "キー": ""
  },
  {
    "枠名": "【1ヶ月記念歌枠】あっという間だね、ありがとう #妃玖ノ記録【妃玖/RKmusic/Fused】",
    "song_id": "S0339",
    "補足情報": "",
    "歌唱順": "14",
    "配信日": "2026-03-22",
    "枠URL": "https://www.youtube.com/live/13_IyqNjdFQ?t=6605",
    "曲終了時間": "",
    "コラボ相手様": "なし",
    "キー": ""
  },
  {
    "枠名": "【1ヶ月記念歌枠】あっという間だね、ありがとう #妃玖ノ記録【妃玖/RKmusic/Fused】",
    "song_id": "S0177",
    "補足情報": "",
    "歌唱順": "15",
    "配信日": "2026-03-22",
    "枠URL": "https://www.youtube.com/live/13_IyqNjdFQ?t=6873",
    "曲終了時間": "",
    "コラボ相手様": "なし",
    "キー": ""
  },
  {
    "枠名": "【1ヶ月記念歌枠】あっという間だね、ありがとう #妃玖ノ記録【妃玖/RKmusic/Fused】",
    "song_id": "S0393",
    "補足情報": "",
    "歌唱順": "16",
    "配信日": "2026-03-22",
    "枠URL": "https://www.youtube.com/live/13_IyqNjdFQ?t=7079",
    "曲終了時間": "",
    "コラボ相手様": "なし",
    "キー": ""
  },
  {
    "枠名": "【平成縛り歌雑！】平成に戻るってガーチャー？ #妃玖ノ記録【妃玖/RKmusic/Fused】",
    "song_id": "S0745",
    "補足情報": "",
    "歌唱順": "1",
    "配信日": "2026-04-02",
    "枠URL": "https://www.youtube.com/live/Sgct4PszV-E?t=715",
    "曲終了時間": "",
    "コラボ相手様": "なし",
    "キー": ""
  },
  {
    "枠名": "【平成縛り歌雑！】平成に戻るってガーチャー？ #妃玖ノ記録【妃玖/RKmusic/Fused】",
    "song_id": "S0746",
    "補足情報": "",
    "歌唱順": "2",
    "配信日": "2026-04-02",
    "枠URL": "https://www.youtube.com/live/Sgct4PszV-E?t=1299",
    "曲終了時間": "",
    "コラボ相手様": "なし",
    "キー": ""
  },
  {
    "枠名": "【平成縛り歌雑！】平成に戻るってガーチャー？ #妃玖ノ記録【妃玖/RKmusic/Fused】",
    "song_id": "S0238",
    "補足情報": "",
    "歌唱順": "3",
    "配信日": "2026-04-02",
    "枠URL": "https://www.youtube.com/live/Sgct4PszV-E?t=3804",
    "曲終了時間": "",
    "コラボ相手様": "なし",
    "キー": ""
  },
  {
    "枠名": "【平成縛り歌雑！】平成に戻るってガーチャー？ #妃玖ノ記録【妃玖/RKmusic/Fused】",
    "song_id": "S0060",
    "補足情報": "",
    "歌唱順": "4",
    "配信日": "2026-04-02",
    "枠URL": "https://www.youtube.com/live/Sgct4PszV-E?t=4107",
    "曲終了時間": "",
    "コラボ相手様": "なし",
    "キー": ""
  },
  {
    "枠名": "【平成縛り歌雑！】平成に戻るってガーチャー？ #妃玖ノ記録【妃玖/RKmusic/Fused】",
    "song_id": "S0747",
    "補足情報": "",
    "歌唱順": "5",
    "配信日": "2026-04-02",
    "枠URL": "https://www.youtube.com/live/Sgct4PszV-E?t=7542",
    "曲終了時間": "",
    "コラボ相手様": "なし",
    "キー": ""
  },
  {
    "枠名": "【平成縛り歌雑！】平成に戻るってガーチャー？ #妃玖ノ記録【妃玖/RKmusic/Fused】",
    "song_id": "S0490",
    "補足情報": "",
    "歌唱順": "6",
    "配信日": "2026-04-02",
    "枠URL": "https://www.youtube.com/live/Sgct4PszV-E?t=7828",
    "曲終了時間": "",
    "コラボ相手様": "なし",
    "キー": ""
  },
  {
    "枠名": "【平成縛り歌雑！】平成に戻るってガーチャー？ #妃玖ノ記録【妃玖/RKmusic/Fused】",
    "song_id": "S0748",
    "補足情報": "",
    "歌唱順": "7",
    "配信日": "2026-04-02",
    "枠URL": "https://www.youtube.com/live/Sgct4PszV-E?t=8160",
    "曲終了時間": "",
    "コラボ相手様": "なし",
    "キー": ""
  },
  {
    "枠名": "【平成縛り歌雑！】平成に戻るってガーチャー？ #妃玖ノ記録【妃玖/RKmusic/Fused】",
    "song_id": "S0676",
    "補足情報": "",
    "歌唱順": "8",
    "配信日": "2026-04-02",
    "枠URL": "https://www.youtube.com/live/Sgct4PszV-E?t=9060",
    "曲終了時間": "",
    "コラボ相手様": "なし",
    "キー": ""
  },
  {
    "枠名": "【平成縛り歌雑！】平成に戻るってガーチャー？ #妃玖ノ記録【妃玖/RKmusic/Fused】",
    "song_id": "S0749",
    "補足情報": "",
    "歌唱順": "9",
    "配信日": "2026-04-02",
    "枠URL": "https://www.youtube.com/live/Sgct4PszV-E?t=10374",
    "曲終了時間": "",
    "コラボ相手様": "なし",
    "キー": ""
  },
  {
    "枠名": "【#RKMusic歌枠リレー】盛り上がってこうぜ！！ #妃玖ノ記録【妃玖/RKmusic/Fused】",
    "song_id": "S0770",
    "補足情報": "#RKMusic歌枠リレー",
    "歌唱順": "1",
    "配信日": "2026-04-05",
    "枠URL": "https://www.youtube.com/live/69kPA648m68?t=76",
    "曲終了時間": "",
    "コラボ相手様": "なし",
    "キー": ""
  },
  {
    "枠名": "【#RKMusic歌枠リレー】盛り上がってこうぜ！！ #妃玖ノ記録【妃玖/RKmusic/Fused】",
    "song_id": "S0771",
    "補足情報": "#RKMusic歌枠リレー",
    "歌唱順": "2",
    "配信日": "2026-04-05",
    "枠URL": "https://www.youtube.com/live/69kPA648m68?t=278",
    "曲終了時間": "",
    "コラボ相手様": "なし",
    "キー": ""
  },
  {
    "枠名": "【#RKMusic歌枠リレー】盛り上がってこうぜ！！ #妃玖ノ記録【妃玖/RKmusic/Fused】",
    "song_id": "S0772",
    "補足情報": "#RKMusic歌枠リレー",
    "歌唱順": "3",
    "配信日": "2026-04-05",
    "枠URL": "https://www.youtube.com/live/69kPA648m68?t=537",
    "曲終了時間": "",
    "コラボ相手様": "なし",
    "キー": ""
  },
  {
    "枠名": "【#RKMusic歌枠リレー】盛り上がってこうぜ！！ #妃玖ノ記録【妃玖/RKmusic/Fused】",
    "song_id": "S0773",
    "補足情報": "#RKMusic歌枠リレー",
    "歌唱順": "4",
    "配信日": "2026-04-05",
    "枠URL": "https://www.youtube.com/live/69kPA648m68?t=934",
    "曲終了時間": "",
    "コラボ相手様": "なし",
    "キー": ""
  },
  {
    "枠名": "【#RKMusic歌枠リレー】盛り上がってこうぜ！！ #妃玖ノ記録【妃玖/RKmusic/Fused】",
    "song_id": "S0774",
    "補足情報": "#RKMusic歌枠リレー",
    "歌唱順": "5",
    "配信日": "2026-04-05",
    "枠URL": "https://www.youtube.com/live/69kPA648m68?t=1222",
    "曲終了時間": "",
    "コラボ相手様": "なし",
    "キー": ""
  },
  {
    "枠名": "【#RKMusic歌枠リレー】盛り上がってこうぜ！！ #妃玖ノ記録【妃玖/RKmusic/Fused】",
    "song_id": "S0775",
    "補足情報": "#RKMusic歌枠リレー",
    "歌唱順": "6",
    "配信日": "2026-04-05",
    "枠URL": "https://www.youtube.com/live/69kPA648m68?t=1464",
    "曲終了時間": "",
    "コラボ相手様": "なし",
    "キー": ""
  },
  {
    "枠名": "【可能？】睡眠導入ってやつだよ #妃玖ノ記録【妃玖/RKmusic/Fused】",
    "song_id": "S0802",
    "補足情報": "",
    "歌唱順": "1",
    "配信日": "2026-04-07",
    "枠URL": "https://www.youtube.com/live/dSXx4u_gBkY?t=429",
    "曲終了時間": "",
    "コラボ相手様": "なし",
    "キー": ""
  },
  {
    "枠名": "【可能？】睡眠導入ってやつだよ #妃玖ノ記録【妃玖/RKmusic/Fused】",
    "song_id": "S0463",
    "補足情報": "",
    "歌唱順": "2",
    "配信日": "2026-04-07",
    "枠URL": "https://www.youtube.com/live/dSXx4u_gBkY?t=1177",
    "曲終了時間": "",
    "コラボ相手様": "なし",
    "キー": ""
  },
  {
    "枠名": "【可能？】睡眠導入ってやつだよ #妃玖ノ記録【妃玖/RKmusic/Fused】",
    "song_id": "S0011",
    "補足情報": "",
    "歌唱順": "3",
    "配信日": "2026-04-07",
    "枠URL": "https://www.youtube.com/live/dSXx4u_gBkY?t=1837",
    "曲終了時間": "",
    "コラボ相手様": "なし",
    "キー": ""
  },
  {
    "枠名": "【可能？】睡眠導入ってやつだよ #妃玖ノ記録【妃玖/RKmusic/Fused】",
    "song_id": "S0328",
    "補足情報": "",
    "歌唱順": "4",
    "配信日": "2026-04-07",
    "枠URL": "https://www.youtube.com/live/dSXx4u_gBkY?t=2625",
    "曲終了時間": "",
    "コラボ相手様": "なし",
    "キー": ""
  },
  {
    "枠名": "【可能？】睡眠導入ってやつだよ #妃玖ノ記録【妃玖/RKmusic/Fused】",
    "song_id": "S0191",
    "補足情報": "",
    "歌唱順": "5",
    "配信日": "2026-04-07",
    "枠URL": "https://www.youtube.com/live/dSXx4u_gBkY?t=2874",
    "曲終了時間": "",
    "コラボ相手様": "なし",
    "キー": ""
  },
  {
    "枠名": "【可能？】睡眠導入ってやつだよ #妃玖ノ記録【妃玖/RKmusic/Fused】",
    "song_id": "S0803",
    "補足情報": "",
    "歌唱順": "6",
    "配信日": "2026-04-07",
    "枠URL": "https://www.youtube.com/live/dSXx4u_gBkY?t=3129",
    "曲終了時間": "",
    "コラボ相手様": "なし",
    "キー": ""
  },
  {
    "枠名": "【可能？】睡眠導入ってやつだよ #妃玖ノ記録【妃玖/RKmusic/Fused】",
    "song_id": "S0804",
    "補足情報": "",
    "歌唱順": "7",
    "配信日": "2026-04-07",
    "枠URL": "https://www.youtube.com/live/dSXx4u_gBkY?t=3538",
    "曲終了時間": "",
    "コラボ相手様": "なし",
    "キー": ""
  },
  {
    "枠名": "【可能？】睡眠導入ってやつだよ #妃玖ノ記録【妃玖/RKmusic/Fused】",
    "song_id": "S0080",
    "補足情報": "",
    "歌唱順": "8",
    "配信日": "2026-04-07",
    "枠URL": "https://www.youtube.com/live/dSXx4u_gBkY?t=4714",
    "曲終了時間": "",
    "コラボ相手様": "なし",
    "キー": ""
  },
  {
    "枠名": "【可能？】睡眠導入ってやつだよ #妃玖ノ記録【妃玖/RKmusic/Fused】",
    "song_id": "S0465",
    "補足情報": "",
    "歌唱順": "9",
    "配信日": "2026-04-07",
    "枠URL": "https://www.youtube.com/live/dSXx4u_gBkY?t=5003",
    "曲終了時間": "",
    "コラボ相手様": "なし",
    "キー": ""
  },
  {
    "枠名": "【可能？】睡眠導入ってやつだよ #妃玖ノ記録【妃玖/RKmusic/Fused】",
    "song_id": "S0287",
    "補足情報": "",
    "歌唱順": "10",
    "配信日": "2026-04-07",
    "枠URL": "https://www.youtube.com/live/dSXx4u_gBkY?t=5303",
    "曲終了時間": "",
    "コラボ相手様": "なし",
    "キー": ""
  },
  {
    "枠名": "【可能？】睡眠導入ってやつだよ #妃玖ノ記録【妃玖/RKmusic/Fused】",
    "song_id": "S0741",
    "補足情報": "",
    "歌唱順": "11",
    "配信日": "2026-04-07",
    "枠URL": "https://www.youtube.com/live/dSXx4u_gBkY?t=5645",
    "曲終了時間": "",
    "コラボ相手様": "なし",
    "キー": ""
  },
  {
    "枠名": "【可能？】睡眠導入ってやつだよ #妃玖ノ記録【妃玖/RKmusic/Fused】",
    "song_id": "S0805",
    "補足情報": "",
    "歌唱順": "12",
    "配信日": "2026-04-07",
    "枠URL": "https://www.youtube.com/live/dSXx4u_gBkY?t=7205",
    "曲終了時間": "",
    "コラボ相手様": "なし",
    "キー": ""
  },
  {
    "枠名": "【可能？】睡眠導入ってやつだよ #妃玖ノ記録【妃玖/RKmusic/Fused】",
    "song_id": "S0210",
    "補足情報": "",
    "歌唱順": "13",
    "配信日": "2026-04-07",
    "枠URL": "https://www.youtube.com/live/dSXx4u_gBkY?t=8276",
    "曲終了時間": "",
    "コラボ相手様": "なし",
    "キー": ""
  },
  {
    "枠名": "【可能？】睡眠導入ってやつだよ #妃玖ノ記録【妃玖/RKmusic/Fused】",
    "song_id": "S0480",
    "補足情報": "",
    "歌唱順": "14",
    "配信日": "2026-04-07",
    "枠URL": "https://www.youtube.com/live/dSXx4u_gBkY?t=8739",
    "曲終了時間": "",
    "コラボ相手様": "なし",
    "キー": ""
  },
  {
    "枠名": "【可能？】睡眠導入ってやつだよ #妃玖ノ記録【妃玖/RKmusic/Fused】",
    "song_id": "S0806",
    "補足情報": "",
    "歌唱順": "15",
    "配信日": "2026-04-07",
    "枠URL": "https://www.youtube.com/live/dSXx4u_gBkY?t=9088",
    "曲終了時間": "",
    "コラボ相手様": "なし",
    "キー": ""
  },
  {
    "枠名": "【可能？】睡眠導入ってやつだよ #妃玖ノ記録【妃玖/RKmusic/Fused】",
    "song_id": "S0146",
    "補足情報": "",
    "歌唱順": "16",
    "配信日": "2026-04-07",
    "枠URL": "https://www.youtube.com/live/dSXx4u_gBkY?t=10484",
    "曲終了時間": "",
    "コラボ相手様": "なし",
    "キー": ""
  },
  {
    "枠名": "【可能？】睡眠導入ってやつだよ #妃玖ノ記録【妃玖/RKmusic/Fused】",
    "song_id": "S0476",
    "補足情報": "",
    "歌唱順": "17",
    "配信日": "2026-04-07",
    "枠URL": "https://www.youtube.com/live/dSXx4u_gBkY?t=10809",
    "曲終了時間": "",
    "コラボ相手様": "なし",
    "キー": ""
  },
  {
    "枠名": "【歌枠】ボカロ縛り歌枠！  #妃玖ノ記録【妃玖/RKmusic/Fused】",
    "song_id": "S0113",
    "補足情報": "",
    "歌唱順": "1",
    "配信日": "2026-04-12",
    "枠URL": "https://www.youtube.com/live/1f_AF0xHo_c?t=512",
    "曲終了時間": "",
    "コラボ相手様": "なし",
    "キー": ""
  },
  {
    "枠名": "【歌枠】ボカロ縛り歌枠！  #妃玖ノ記録【妃玖/RKmusic/Fused】",
    "song_id": "S0807",
    "補足情報": "",
    "歌唱順": "2",
    "配信日": "2026-04-12",
    "枠URL": "https://www.youtube.com/live/1f_AF0xHo_c?t=745",
    "曲終了時間": "",
    "コラボ相手様": "なし",
    "キー": ""
  },
  {
    "枠名": "【歌枠】ボカロ縛り歌枠！  #妃玖ノ記録【妃玖/RKmusic/Fused】",
    "song_id": "S0106",
    "補足情報": "",
    "歌唱順": "3",
    "配信日": "2026-04-12",
    "枠URL": "https://www.youtube.com/live/1f_AF0xHo_c?t=1840",
    "曲終了時間": "",
    "コラボ相手様": "なし",
    "キー": ""
  },
  {
    "枠名": "【歌枠】ボカロ縛り歌枠！  #妃玖ノ記録【妃玖/RKmusic/Fused】",
    "song_id": "S0109",
    "補足情報": "",
    "歌唱順": "4",
    "配信日": "2026-04-12",
    "枠URL": "https://www.youtube.com/live/1f_AF0xHo_c?t=2050",
    "曲終了時間": "",
    "コラボ相手様": "なし",
    "キー": ""
  },
  {
    "枠名": "【歌枠】ボカロ縛り歌枠！  #妃玖ノ記録【妃玖/RKmusic/Fused】",
    "song_id": "S0808",
    "補足情報": "",
    "歌唱順": "5",
    "配信日": "2026-04-12",
    "枠URL": "https://www.youtube.com/live/1f_AF0xHo_c?t=2812",
    "曲終了時間": "",
    "コラボ相手様": "なし",
    "キー": ""
  },
  {
    "枠名": "【歌枠】ボカロ縛り歌枠！  #妃玖ノ記録【妃玖/RKmusic/Fused】",
    "song_id": "S0809",
    "補足情報": "",
    "歌唱順": "6",
    "配信日": "2026-04-12",
    "枠URL": "https://www.youtube.com/live/1f_AF0xHo_c?t=3457",
    "曲終了時間": "",
    "コラボ相手様": "なし",
    "キー": ""
  },
  {
    "枠名": "【歌枠】ボカロ縛り歌枠！  #妃玖ノ記録【妃玖/RKmusic/Fused】",
    "song_id": "S0810",
    "補足情報": "",
    "歌唱順": "7",
    "配信日": "2026-04-12",
    "枠URL": "https://www.youtube.com/live/1f_AF0xHo_c?t=3801",
    "曲終了時間": "",
    "コラボ相手様": "なし",
    "キー": ""
  },
  {
    "枠名": "【歌枠】ボカロ縛り歌枠！  #妃玖ノ記録【妃玖/RKmusic/Fused】",
    "song_id": "S0811",
    "補足情報": "",
    "歌唱順": "8",
    "配信日": "2026-04-12",
    "枠URL": "https://www.youtube.com/live/1f_AF0xHo_c?t=4257",
    "曲終了時間": "",
    "コラボ相手様": "なし",
    "キー": ""
  },
  {
    "枠名": "【歌枠】ボカロ縛り歌枠！  #妃玖ノ記録【妃玖/RKmusic/Fused】",
    "song_id": "S0812",
    "補足情報": "",
    "歌唱順": "9",
    "配信日": "2026-04-12",
    "枠URL": "https://www.youtube.com/live/1f_AF0xHo_c?t=4485",
    "曲終了時間": "",
    "コラボ相手様": "なし",
    "キー": ""
  },
  {
    "枠名": "【歌枠】ボカロ縛り歌枠！  #妃玖ノ記録【妃玖/RKmusic/Fused】",
    "song_id": "S0816",
    "補足情報": "",
    "歌唱順": "10",
    "配信日": "2026-04-12",
    "枠URL": "https://www.youtube.com/live/1f_AF0xHo_c?t=4814",
    "曲終了時間": "",
    "コラボ相手様": "なし",
    "キー": ""
  },
  {
    "枠名": "【歌枠】ボカロ縛り歌枠！  #妃玖ノ記録【妃玖/RKmusic/Fused】",
    "song_id": "S0813",
    "補足情報": "",
    "歌唱順": "11",
    "配信日": "2026-04-12",
    "枠URL": "https://www.youtube.com/live/1f_AF0xHo_c?t=5492",
    "曲終了時間": "",
    "コラボ相手様": "なし",
    "キー": ""
  },
  {
    "枠名": "【歌枠】ボカロ縛り歌枠！  #妃玖ノ記録【妃玖/RKmusic/Fused】",
    "song_id": "S0051",
    "補足情報": "",
    "歌唱順": "12",
    "配信日": "2026-04-12",
    "枠URL": "https://www.youtube.com/live/1f_AF0xHo_c?t=5703",
    "曲終了時間": "",
    "コラボ相手様": "なし",
    "キー": ""
  },
  {
    "枠名": "【歌枠】ボカロ縛り歌枠！  #妃玖ノ記録【妃玖/RKmusic/Fused】",
    "song_id": "S0814",
    "補足情報": "",
    "歌唱順": "13",
    "配信日": "2026-04-12",
    "枠URL": "https://www.youtube.com/live/1f_AF0xHo_c?t=6380",
    "曲終了時間": "",
    "コラボ相手様": "なし",
    "キー": ""
  },
  {
    "枠名": "【歌枠】ボカロ縛り歌枠！  #妃玖ノ記録【妃玖/RKmusic/Fused】",
    "song_id": "S0727",
    "補足情報": "",
    "歌唱順": "14",
    "配信日": "2026-04-12",
    "枠URL": "https://www.youtube.com/live/1f_AF0xHo_c?t=6653",
    "曲終了時間": "",
    "コラボ相手様": "なし",
    "キー": ""
  },
  {
    "枠名": "【歌枠】ボカロ縛り歌枠！  #妃玖ノ記録【妃玖/RKmusic/Fused】",
    "song_id": "S0815",
    "補足情報": "",
    "歌唱順": "15",
    "配信日": "2026-04-12",
    "枠URL": "https://www.youtube.com/live/1f_AF0xHo_c?t=6894",
    "曲終了時間": "",
    "コラボ相手様": "なし",
    "キー": ""
  },
  {
    "枠名": "【歌枠】ボカロ縛り歌枠！  #妃玖ノ記録【妃玖/RKmusic/Fused】",
    "song_id": "S0297",
    "補足情報": "",
    "歌唱順": "16",
    "配信日": "2026-04-12",
    "枠URL": "https://www.youtube.com/live/1f_AF0xHo_c?t=7164",
    "曲終了時間": "",
    "コラボ相手様": "なし",
    "キー": ""
  },
  {
    "枠名": "【歌枠】ボカロ縛り歌枠！  #妃玖ノ記録【妃玖/RKmusic/Fused】",
    "song_id": "S0250",
    "補足情報": "",
    "歌唱順": "17",
    "配信日": "2026-04-12",
    "枠URL": "https://www.youtube.com/live/1f_AF0xHo_c?t=7975",
    "曲終了時間": "",
    "コラボ相手様": "なし",
    "キー": ""
  },
  {
    "枠名": "【歌枠】ボカロ縛り歌枠！  #妃玖ノ記録【妃玖/RKmusic/Fused】",
    "song_id": "S0562",
    "補足情報": "",
    "歌唱順": "18",
    "配信日": "2026-04-12",
    "枠URL": "https://www.youtube.com/live/1f_AF0xHo_c?t=8220",
    "曲終了時間": "",
    "コラボ相手様": "なし",
    "キー": ""
  },
  {
    "枠名": "【歌枠】様々な歌を歌わせていただくなど。  #妃玖ノ記録【妃玖/RKmusic/Fused】",
    "song_id": "S0409",
    "補足情報": "",
    "歌唱順": "1",
    "配信日": "2026-04-16",
    "枠URL": "https://www.youtube.com/live/_8Cf-6TVijg?t=561",
    "曲終了時間": "",
    "コラボ相手様": "なし",
    "キー": ""
  },
  {
    "枠名": "【歌枠】様々な歌を歌わせていただくなど。  #妃玖ノ記録【妃玖/RKmusic/Fused】",
    "song_id": "S0015",
    "補足情報": "",
    "歌唱順": "2",
    "配信日": "2026-04-16",
    "枠URL": "https://www.youtube.com/live/_8Cf-6TVijg?t=830",
    "曲終了時間": "",
    "コラボ相手様": "なし",
    "キー": ""
  },
  {
    "枠名": "【歌枠】様々な歌を歌わせていただくなど。  #妃玖ノ記録【妃玖/RKmusic/Fused】",
    "song_id": "S0822",
    "補足情報": "",
    "歌唱順": "3",
    "配信日": "2026-04-16",
    "枠URL": "https://www.youtube.com/live/_8Cf-6TVijg?t=1650",
    "曲終了時間": "",
    "コラボ相手様": "なし",
    "キー": ""
  },
  {
    "枠名": "【歌枠】様々な歌を歌わせていただくなど。  #妃玖ノ記録【妃玖/RKmusic/Fused】",
    "song_id": "S0823",
    "補足情報": "",
    "歌唱順": "4",
    "配信日": "2026-04-16",
    "枠URL": "https://www.youtube.com/live/_8Cf-6TVijg?t=1973",
    "曲終了時間": "",
    "コラボ相手様": "なし",
    "キー": ""
  },
  {
    "枠名": "【歌枠】様々な歌を歌わせていただくなど。  #妃玖ノ記録【妃玖/RKmusic/Fused】",
    "song_id": "S0824",
    "補足情報": "",
    "歌唱順": "5",
    "配信日": "2026-04-16",
    "枠URL": "https://www.youtube.com/live/_8Cf-6TVijg?t=2516",
    "曲終了時間": "",
    "コラボ相手様": "なし",
    "キー": ""
  },
  {
    "枠名": "【歌枠】様々な歌を歌わせていただくなど。  #妃玖ノ記録【妃玖/RKmusic/Fused】",
    "song_id": "S0404",
    "補足情報": "",
    "歌唱順": "6",
    "配信日": "2026-04-16",
    "枠URL": "https://www.youtube.com/live/_8Cf-6TVijg?t=3859",
    "曲終了時間": "",
    "コラボ相手様": "なし",
    "キー": ""
  },
  {
    "枠名": "【歌枠】様々な歌を歌わせていただくなど。  #妃玖ノ記録【妃玖/RKmusic/Fused】",
    "song_id": "S0825",
    "補足情報": "",
    "歌唱順": "7",
    "配信日": "2026-04-16",
    "枠URL": "https://www.youtube.com/live/_8Cf-6TVijg?t=4086",
    "曲終了時間": "",
    "コラボ相手様": "なし",
    "キー": ""
  },
  {
    "枠名": "【歌枠】様々な歌を歌わせていただくなど。  #妃玖ノ記録【妃玖/RKmusic/Fused】",
    "song_id": "S0826",
    "補足情報": "",
    "歌唱順": "8",
    "配信日": "2026-04-16",
    "枠URL": "https://www.youtube.com/live/_8Cf-6TVijg?t=4266",
    "曲終了時間": "",
    "コラボ相手様": "なし",
    "キー": ""
  },
  {
    "枠名": "【歌枠】様々な歌を歌わせていただくなど。  #妃玖ノ記録【妃玖/RKmusic/Fused】",
    "song_id": "S0827",
    "補足情報": "",
    "歌唱順": "9",
    "配信日": "2026-04-16",
    "枠URL": "https://www.youtube.com/live/_8Cf-6TVijg?t=4959",
    "曲終了時間": "",
    "コラボ相手様": "なし",
    "キー": ""
  },
  {
    "枠名": "【歌枠】様々な歌を歌わせていただくなど。  #妃玖ノ記録【妃玖/RKmusic/Fused】",
    "song_id": "S0828",
    "補足情報": "",
    "歌唱順": "10",
    "配信日": "2026-04-16",
    "枠URL": "https://www.youtube.com/live/_8Cf-6TVijg?t=5644",
    "曲終了時間": "",
    "コラボ相手様": "なし",
    "キー": ""
  },
  {
    "枠名": "【歌枠】様々な歌を歌わせていただくなど。  #妃玖ノ記録【妃玖/RKmusic/Fused】",
    "song_id": "S0766",
    "補足情報": "",
    "歌唱順": "11",
    "配信日": "2026-04-16",
    "枠URL": "https://www.youtube.com/live/_8Cf-6TVijg?t=6001",
    "曲終了時間": "",
    "コラボ相手様": "なし",
    "キー": ""
  },
  {
    "枠名": "【歌枠】様々な歌を歌わせていただくなど。  #妃玖ノ記録【妃玖/RKmusic/Fused】",
    "song_id": "S0653",
    "補足情報": "",
    "歌唱順": "12",
    "配信日": "2026-04-16",
    "枠URL": "https://www.youtube.com/live/_8Cf-6TVijg?t=6439",
    "曲終了時間": "",
    "コラボ相手様": "なし",
    "キー": ""
  },
  {
    "枠名": "【歌枠】様々な歌を歌わせていただくなど。  #妃玖ノ記録【妃玖/RKmusic/Fused】",
    "song_id": "S0829",
    "補足情報": "",
    "歌唱順": "13",
    "配信日": "2026-04-16",
    "枠URL": "https://www.youtube.com/live/_8Cf-6TVijg?t=7034",
    "曲終了時間": "",
    "コラボ相手様": "なし",
    "キー": ""
  },
  {
    "枠名": "【歌枠】様々な歌を歌わせていただくなど。  #妃玖ノ記録【妃玖/RKmusic/Fused】",
    "song_id": "S0830",
    "補足情報": "",
    "歌唱順": "14",
    "配信日": "2026-04-16",
    "枠URL": "https://www.youtube.com/live/_8Cf-6TVijg?t=7325",
    "曲終了時間": "",
    "コラボ相手様": "なし",
    "キー": ""
  },
  {
    "枠名": "【歌枠】様々な歌を歌わせていただくなど。  #妃玖ノ記録【妃玖/RKmusic/Fused】",
    "song_id": "S0033",
    "補足情報": "",
    "歌唱順": "15",
    "配信日": "2026-04-16",
    "枠URL": "https://www.youtube.com/live/_8Cf-6TVijg?t=7848",
    "曲終了時間": "",
    "コラボ相手様": "なし",
    "キー": ""
  },
  {
    "枠名": "【歌枠】ピアノ伴奏オンリーだわよ  #妃玖ノ記録【妃玖/RKmusic/Fused】",
    "song_id": "S0094",
    "補足情報": "ピアノ伴奏",
    "歌唱順": "1",
    "配信日": "2026-04-20",
    "枠URL": "https://www.youtube.com/live/ktZrlo7XC-U?t=160",
    "曲終了時間": "",
    "コラボ相手様": "なし",
    "キー": ""
  },
  {
    "枠名": "【歌枠】ピアノ伴奏オンリーだわよ  #妃玖ノ記録【妃玖/RKmusic/Fused】",
    "song_id": "S0314",
    "補足情報": "ピアノ伴奏",
    "歌唱順": "2",
    "配信日": "2026-04-20",
    "枠URL": "https://www.youtube.com/live/ktZrlo7XC-U?t=458",
    "曲終了時間": "",
    "コラボ相手様": "なし",
    "キー": ""
  },
  {
    "枠名": "【歌枠】ピアノ伴奏オンリーだわよ  #妃玖ノ記録【妃玖/RKmusic/Fused】",
    "song_id": "S0245",
    "補足情報": "ピアノ伴奏",
    "歌唱順": "3",
    "配信日": "2026-04-20",
    "枠URL": "https://www.youtube.com/live/ktZrlo7XC-U?t=1251",
    "曲終了時間": "",
    "コラボ相手様": "なし",
    "キー": ""
  },
  {
    "枠名": "【歌枠】ピアノ伴奏オンリーだわよ  #妃玖ノ記録【妃玖/RKmusic/Fused】",
    "song_id": "S0260",
    "補足情報": "ピアノ伴奏",
    "歌唱順": "4",
    "配信日": "2026-04-20",
    "枠URL": "https://www.youtube.com/live/ktZrlo7XC-U?t=1603",
    "曲終了時間": "",
    "コラボ相手様": "なし",
    "キー": ""
  },
  {
    "枠名": "【歌枠】ピアノ伴奏オンリーだわよ  #妃玖ノ記録【妃玖/RKmusic/Fused】",
    "song_id": "S0426",
    "補足情報": "ピアノ伴奏",
    "歌唱順": "5",
    "配信日": "2026-04-20",
    "枠URL": "https://www.youtube.com/live/ktZrlo7XC-U?t=2725",
    "曲終了時間": "",
    "コラボ相手様": "なし",
    "キー": ""
  },
  {
    "枠名": "【歌枠】ピアノ伴奏オンリーだわよ  #妃玖ノ記録【妃玖/RKmusic/Fused】",
    "song_id": "S0348",
    "補足情報": "ピアノ伴奏",
    "歌唱順": "6",
    "配信日": "2026-04-20",
    "枠URL": "https://www.youtube.com/live/ktZrlo7XC-U?t=3042",
    "曲終了時間": "",
    "コラボ相手様": "なし",
    "キー": ""
  },
  {
    "枠名": "【歌枠】ピアノ伴奏オンリーだわよ  #妃玖ノ記録【妃玖/RKmusic/Fused】",
    "song_id": "S0076",
    "補足情報": "ピアノ伴奏",
    "歌唱順": "7",
    "配信日": "2026-04-20",
    "枠URL": "https://www.youtube.com/live/ktZrlo7XC-U?t=3273",
    "曲終了時間": "",
    "コラボ相手様": "なし",
    "キー": ""
  },
  {
    "枠名": "【歌枠】ピアノ伴奏オンリーだわよ  #妃玖ノ記録【妃玖/RKmusic/Fused】",
    "song_id": "S0108",
    "補足情報": "ピアノ伴奏",
    "歌唱順": "8",
    "配信日": "2026-04-20",
    "枠URL": "https://www.youtube.com/live/ktZrlo7XC-U?t=4294",
    "曲終了時間": "",
    "コラボ相手様": "なし",
    "キー": ""
  },
  {
    "枠名": "【歌枠】ピアノ伴奏オンリーだわよ  #妃玖ノ記録【妃玖/RKmusic/Fused】",
    "song_id": "S0472",
    "補足情報": "",
    "歌唱順": "9",
    "配信日": "2026-04-20",
    "枠URL": "https://www.youtube.com/live/ktZrlo7XC-U?t=6770",
    "曲終了時間": "",
    "コラボ相手様": "なし",
    "キー": ""
  }
]